glvar/__init__.py
glvar/__main__.py
glvar/cli.py
glvar-0.5.dist-info/licenses/LICENSE
glvar-0.5.dist-info/METADATA
glvar-0.5.dist-info/WHEEL
glvar-0.5.dist-info/entry_points.txt
glvar-0.5.dist-info/top_level.txt
glvar-0.5.dist-info/RECORD
