Metadata-Version: 2.4
Name: glvar
Version: 0.5
Summary: Fetch variables from GitLab and inject into environment for local commands
Author-email: Oskar Skoog <oskar.skoog@agama.tv>
Project-URL: Homepage, https://github.com/Agama-Technologies/glvar
Project-URL: Changelog, https://github.com/Agama-Technologies/glvar/releases
Project-URL: Issues, https://github.com/Agama-Technologies/glvar/issues
Project-URL: CI, https://github.com/Agama-Technologies/glvar/actions
Requires-Python: >=3.10
License-File: LICENSE
Requires-Dist: requests<3
Requires-Dist: rich
Requires-Dist: click
Requires-Dist: keyring
Provides-Extra: test
Requires-Dist: ruff; extra == "test"
Dynamic: license-file
